modelmirror/__init__.py
modelmirror/mirror.py
modelmirror/reflections.py
modelmirror/class_provider/__init__.py
modelmirror/class_provider/class_reference.py
modelmirror/class_provider/class_register.py
modelmirror/class_provider/class_scanner.py
modelmirror/instance/__init__.py
modelmirror/instance/instance_container.py
modelmirror/instance/instance_properties.py
modelmirror/instance/reference_service.py
modelmirror/instance/validation_service.py
modelmirror/parser/__init__.py
modelmirror/parser/code_link.py
modelmirror/parser/code_link_parser.py
modelmirror/parser/default_code_link_parser.py
modelmirror/parser/default_model_link_parser.py
modelmirror/parser/default_secret_parser.py
modelmirror/parser/mirror_secret.py
modelmirror/parser/model_link.py
modelmirror/parser/model_link_parser.py
modelmirror/parser/secret_parser.py
modelmirror/reflection/__init__.py
modelmirror/reflection/reflection_engine.py
modelmirror/reflection/reflection_registry.py
modelmirror/scan/__init__.py
modelmirror/secrets/__init__.py
modelmirror/secrets/secret_factory.py
modelmirror/singleton/__init__.py
modelmirror/singleton/singleton_manager.py
modelmirror/utils/__init__.py
modelmirror/utils/json_utils.py
modelmirror-0.1.29.dist-info/METADATA
modelmirror-0.1.29.dist-info/WHEEL
modelmirror-0.1.29.dist-info/licenses/LICENSE
modelmirror-0.1.29.dist-info/RECORD
