Metadata-Version: 2.4
Name: modelmirror
Version: 0.1.29
Summary: Model Mirror
Project-URL: Homepage, https://github.com/enyr-srl/modelmirror
Project-URL: Repository, https://github.com/enyr-srl/modelmirror
Project-URL: Issues, https://github.com/enyr-srl/modelmirror/issues
Author-email: Lorenzo Bretto <lorenzo.bretto@enyr.eu>
License-Expression: MIT
License-File: LICENSE
Classifier: License :: OSI Approved :: MIT License
Classifier: Operating System :: OS Independent
Classifier: Programming Language :: Python :: 3
Requires-Python: >=3.10
Requires-Dist: pydantic>=2.0.0
